fwdprop/__init__.py
fwdprop/activations.py
fwdprop/core.py
fwdprop-0.1.7.dist-info/licenses/LICENSE
fwdprop-0.1.7.dist-info/METADATA
fwdprop-0.1.7.dist-info/WHEEL
fwdprop-0.1.7.dist-info/top_level.txt
fwdprop-0.1.7.dist-info/RECORD
