Metadata-Version: 2.4
Name: fwdprop
Version: 0.1.7
Summary: A forward propagation simulator for 3-input networks
Author: Gokulanand M
Author-email: GokulanandM <gokulkvmhs2020@gmail.com>
License: MIT
Classifier: Programming Language :: Python :: 3
Classifier: License :: OSI Approved :: MIT License
Classifier: Operating System :: OS Independent
Requires-Python: >=3.6
License-File: LICENSE
Requires-Dist: numpy
Dynamic: author
Dynamic: license-file
